RobotsTools/__init__.py
RobotsTools/data.py
RobotsTools/genConfigFile.py
RobotsTools/main.py
RobotsTools/shellIntigration.py
RobotsTools/test.sh
RobotsTools/timerOperations.py
RobotsTools/PL/compiler.py
RobotsTools/PL/keywords.txt
RobotsTools/PL/output.txt
RobotsTools/PL/shell.py
RobotsTools/config/getConfigValue.py
RobotsTools/logging/debug.py
RobotsTools/logging/formattedWrite.py
RobotsTools/logging/log.py
RobotsTools/logging/logFile.py
RobotsTools/settings/changeDefaultLogFile.py
robotstools-0.0.6.dist-info/METADATA
robotstools-0.0.6.dist-info/WHEEL
robotstools-0.0.6.dist-info/licenses/LICENSE
robotstools-0.0.6.dist-info/RECORD
